{"filename":"/home/alchemist/git/engine-psx/assets/pre/levels/R1/8x8.png","width":16,"height":16,"layers":[{"cels":[{"bounds":{"height":16,"x":0,"y":0,"width":16},"frame":0,"tilemap":{"height":2,"tiles":[0,0,0,0],"width":2}},{"bounds":{"height":16,"x":0,"y":0,"width":16},"frame":1,"tilemap":{"height":2,"tiles":[1,2,3,4],"width":2}},{"bounds":{"height":16,"x":0,"y":0,"width":16},"frame":2,"tilemap":{"height":2,"tiles":[5,2,6,4],"width":2}},{"bounds":{"height":16,"x":0,"y":0,"width":16},"frame":3,"tilemap":{"height":2,"tiles":[5,7,6,8],"width":2}},{"bounds":{"height":16,"x":0,"y":0,"width":16},"frame":4,"tilemap":{"height":2,"tiles":[9,2,10,4],"width":2}},{"bounds":{"height":16,"x":0,"y":0,"width":16},"frame":5,"tilemap":{"height":2,"tiles":[5,11,6,12],"width":2}},{"bounds":{"height":16,"x":0,"y":0,"width":16},"frame":6,"tilemap":{"height":2,"tiles":[13,14,6,15],"width":2}},{"bounds":{"height":16,"x":0,"y":0,"width":16},"frame":7,"tilemap":{"height":2,"tiles":[13,14,16,4],"width":2}},{"bounds":{"height":16,"x":0,"y":0,"width":16},"frame":8,"tilemap":{"height":2,"tiles":[17,17,17,17],"width":2}},{"bounds":{"height":16,"x":0,"y":0,"width":16},"frame":9,"tilemap":{"height":2,"tiles":[18,14,3,4],"width":2}},{"bounds":{"height":16,"x":0,"y":0,"width":16},"frame":10,"tilemap":{"height":2,"tiles":[13,14,6,4],"width":2}},{"bounds":{"height":16,"x":0,"y":0,"width":16},"frame":11,"tilemap":{"height":2,"tiles":[13,19,6,8],"width":2}},{"bounds":{"height":16,"x":0,"y":0,"width":16},"frame":12,"tilemap":{"height":2,"tiles":[20,14,10,4],"width":2}},{"bounds":{"height":16,"x":0,"y":0,"width":16},"frame":13,"tilemap":{"height":2,"tiles":[13,21,6,12],"width":2}},{"bounds":{"height":16,"x":0,"y":0,"width":16},"frame":14,"tilemap":{"height":2,"tiles":[13,22,6,4],"width":2}},{"bounds":{"height":16,"x":0,"y":0,"width":16},"frame":15,"tilemap":{"height":2,"tiles":[23,14,6,4],"width":2}},{"bounds":{"height":16,"x":0,"y":0,"width":16},"frame":16,"tilemap":{"height":2,"tiles":[24,24,24,24],"width":2}},{"bounds":{"height":16,"x":0,"y":0,"width":16},"frame":17,"tilemap":{"height":2,"tiles":[18,14,25,26],"width":2}},{"bounds":{"height":16,"x":0,"y":0,"width":16},"frame":18,"tilemap":{"height":2,"tiles":[13,14,27,26],"width":2}},{"bounds":{"height":16,"x":0,"y":0,"width":16},"frame":19,"tilemap":{"height":2,"tiles":[13,19,27,28],"width":2}},{"bounds":{"height":16,"x":0,"y":0,"width":16},"frame":20,"tilemap":{"height":2,"tiles":[20,14,29,26],"width":2}},{"bounds":{"height":16,"x":0,"y":0,"width":16},"frame":21,"tilemap":{"height":2,"tiles":[13,21,27,30],"width":2}},{"bounds":{"height":16,"x":0,"y":0,"width":16},"frame":22,"tilemap":{"height":2,"tiles":[13,31,6,4],"width":2}},{"bounds":{"height":16,"x":0,"y":0,"width":16},"frame":23,"tilemap":{"height":2,"tiles":[32,14,6,4],"width":2}},{"bounds":{"height":16,"x":0,"y":0,"width":16},"frame":24,"tilemap":{"height":2,"tiles":[33,34,6,35],"width":2}},{"bounds":{"height":16,"x":0,"y":0,"width":16},"frame":25,"tilemap":{"height":2,"tiles":[0,0,36,37],"width":2}},{"bounds":{"height":16,"x":0,"y":0,"width":16},"frame":26,"tilemap":{"height":2,"tiles":[0,0,38,39],"width":2}},{"bounds":{"height":16,"x":0,"y":0,"width":16},"frame":27,"tilemap":{"height":2,"tiles":[40,41,42,4],"width":2}},{"bounds":{"height":16,"x":0,"y":0,"width":16},"frame":28,"tilemap":{"height":2,"tiles":[43,0,44,45],"width":2}},{"bounds":{"height":16,"x":0,"y":0,"width":16},"frame":29,"tilemap":{"height":2,"tiles":[0,46,47,48],"width":2}},{"bounds":{"height":16,"x":0,"y":0,"width":16},"frame":30,"tilemap":{"height":2,"tiles":[13,49,6,4],"width":2}},{"bounds":{"height":16,"x":0,"y":0,"width":16},"frame":31,"tilemap":{"height":2,"tiles":[50,14,6,4],"width":2}},{"bounds":{"height":16,"x":0,"y":0,"width":16},"frame":32,"tilemap":{"height":2,"tiles":[51,0,52,0],"width":2}},{"bounds":{"height":16,"x":0,"y":0,"width":16},"frame":33,"tilemap":{"height":2,"tiles":[0,53,0,54],"width":2}},{"bounds":{"height":16,"x":0,"y":0,"width":16},"frame":34,"tilemap":{"height":2,"tiles":[55,56,6,57],"width":2}},{"bounds":{"height":16,"x":0,"y":0,"width":16},"frame":35,"tilemap":{"height":2,"tiles":[58,59,60,4],"width":2}},{"bounds":{"height":16,"x":0,"y":0,"width":16},"frame":36,"tilemap":{"height":2,"tiles":[13,61,6,4],"width":2}},{"bounds":{"height":16,"x":0,"y":0,"width":16},"frame":37,"tilemap":{"height":2,"tiles":[62,14,6,4],"width":2}},{"bounds":{"height":16,"x":0,"y":0,"width":16},"frame":38,"tilemap":{"height":2,"tiles":[13,63,6,64],"width":2}},{"bounds":{"height":16,"x":0,"y":0,"width":16},"frame":39,"tilemap":{"height":2,"tiles":[13,65,6,66],"width":2}},{"bounds":{"height":16,"x":0,"y":0,"width":16},"frame":40,"tilemap":{"height":2,"tiles":[67,68,6,4],"width":2}},{"bounds":{"height":16,"x":0,"y":0,"width":16},"frame":41,"tilemap":{"height":2,"tiles":[69,70,6,4],"width":2}},{"bounds":{"height":16,"x":0,"y":0,"width":16},"frame":42,"tilemap":{"height":2,"tiles":[71,14,72,4],"width":2}},{"bounds":{"height":16,"x":0,"y":0,"width":16},"frame":43,"tilemap":{"height":2,"tiles":[73,14,74,4],"width":2}},{"bounds":{"height":16,"x":0,"y":0,"width":16},"frame":44,"tilemap":{"height":2,"tiles":[75,76,6,4],"width":2}},{"bounds":{"height":16,"x":0,"y":0,"width":16},"frame":45,"tilemap":{"height":2,"tiles":[77,78,6,4],"width":2}},{"bounds":{"height":16,"x":0,"y":0,"width":16},"frame":46,"tilemap":{"height":2,"tiles":[79,80,81,82],"width":2}},{"bounds":{"height":16,"x":0,"y":0,"width":16},"frame":47,"tilemap":{"height":2,"tiles":[83,84,85,86],"width":2}},{"bounds":{"height":16,"x":0,"y":0,"width":16},"frame":48,"tilemap":{"height":2,"tiles":[79,84,81,86],"width":2}},{"bounds":{"height":16,"x":0,"y":0,"width":16},"frame":49,"tilemap":{"height":2,"tiles":[83,80,85,82],"width":2}},{"bounds":{"height":16,"x":0,"y":0,"width":16},"frame":50,"tilemap":{"height":2,"tiles":[83,84,6,4],"width":2}},{"bounds":{"height":16,"x":0,"y":0,"width":16},"frame":51,"tilemap":{"height":2,"tiles":[13,14,85,86],"width":2}},{"bounds":{"height":16,"x":0,"y":0,"width":16},"frame":52,"tilemap":{"height":2,"tiles":[79,84,10,4],"width":2}},{"bounds":{"height":16,"x":0,"y":0,"width":16},"frame":53,"tilemap":{"height":2,"tiles":[83,80,6,12],"width":2}},{"bounds":{"height":16,"x":0,"y":0,"width":16},"frame":54,"tilemap":{"height":2,"tiles":[20,14,81,86],"width":2}},{"bounds":{"height":16,"x":0,"y":0,"width":16},"frame":55,"tilemap":{"height":2,"tiles":[13,21,85,82],"width":2}},{"bounds":{"height":16,"x":0,"y":0,"width":16},"frame":56,"tilemap":{"height":2,"tiles":[13,14,6,87],"width":2}},{"bounds":{"height":16,"x":0,"y":0,"width":16},"frame":57,"tilemap":{"height":2,"tiles":[13,14,88,4],"width":2}},{"bounds":{"height":16,"x":0,"y":0,"width":16},"frame":58,"tilemap":{"height":2,"tiles":[13,14,6,89],"width":2}},{"bounds":{"height":16,"x":0,"y":0,"width":16},"frame":59,"tilemap":{"height":2,"tiles":[13,14,90,4],"width":2}},{"bounds":{"height":16,"x":0,"y":0,"width":16},"frame":60,"tilemap":{"height":2,"tiles":[20,21,10,12],"width":2}},{"bounds":{"height":16,"x":0,"y":0,"width":16},"frame":61,"tilemap":{"height":2,"tiles":[79,80,10,12],"width":2}},{"bounds":{"height":16,"x":0,"y":0,"width":16},"frame":62,"tilemap":{"height":2,"tiles":[20,21,81,82],"width":2}},{"bounds":{"height":16,"x":0,"y":0,"width":16},"frame":63,"tilemap":{"height":2,"tiles":[91,0,92,0],"width":2}},{"bounds":{"height":16,"x":0,"y":0,"width":16},"frame":64,"tilemap":{"height":2,"tiles":[0,93,0,94],"width":2}},{"bounds":{"height":16,"x":0,"y":0,"width":16},"frame":65,"tilemap":{"height":2,"tiles":[13,95,96,97],"width":2}},{"bounds":{"height":16,"x":0,"y":0,"width":16},"frame":66,"tilemap":{"height":2,"tiles":[98,14,99,100],"width":2}},{"bounds":{"height":16,"x":0,"y":0,"width":16},"frame":67,"tilemap":{"height":2,"tiles":[13,14,6,101],"width":2}},{"bounds":{"height":16,"x":0,"y":0,"width":16},"frame":68,"tilemap":{"height":2,"tiles":[13,14,102,4],"width":2}},{"bounds":{"height":16,"x":0,"y":0,"width":16},"frame":69,"tilemap":{"height":2,"tiles":[13,103,104,105],"width":2}},{"bounds":{"height":16,"x":0,"y":0,"width":16},"frame":70,"tilemap":{"height":2,"tiles":[106,107,0,0],"width":2}},{"bounds":{"height":16,"x":0,"y":0,"width":16},"frame":71,"tilemap":{"height":2,"tiles":[108,109,0,0],"width":2}},{"bounds":{"height":16,"x":0,"y":0,"width":16},"frame":72,"tilemap":{"height":2,"tiles":[110,14,111,112],"width":2}},{"bounds":{"height":16,"x":0,"y":0,"width":16},"frame":73,"tilemap":{"height":2,"tiles":[113,114,115,0],"width":2}},{"bounds":{"height":16,"x":0,"y":0,"width":16},"frame":74,"tilemap":{"height":2,"tiles":[116,117,0,118],"width":2}},{"bounds":{"height":16,"x":0,"y":0,"width":16},"frame":75,"tilemap":{"height":2,"tiles":[119,120,121,4],"width":2}},{"bounds":{"height":16,"x":0,"y":0,"width":16},"frame":76,"tilemap":{"height":2,"tiles":[122,123,124,125],"width":2}},{"bounds":{"height":16,"x":0,"y":0,"width":16},"frame":77,"tilemap":{"height":2,"tiles":[126,0,127,128],"width":2}},{"bounds":{"height":16,"x":0,"y":0,"width":16},"frame":78,"tilemap":{"height":2,"tiles":[0,0,129,130],"width":2}},{"bounds":{"height":16,"x":0,"y":0,"width":16},"frame":79,"tilemap":{"height":2,"tiles":[0,0,131,132],"width":2}},{"bounds":{"height":16,"x":0,"y":0,"width":16},"frame":80,"tilemap":{"height":2,"tiles":[0,133,134,135],"width":2}},{"bounds":{"height":16,"x":0,"y":0,"width":16},"frame":81,"tilemap":{"height":2,"tiles":[136,137,138,139],"width":2}},{"bounds":{"height":16,"x":0,"y":0,"width":16},"frame":82,"tilemap":{"height":2,"tiles":[140,141,6,142],"width":2}},{"bounds":{"height":16,"x":0,"y":0,"width":16},"frame":83,"tilemap":{"height":2,"tiles":[143,144,145,4],"width":2}},{"bounds":{"height":16,"x":0,"y":0,"width":16},"frame":84,"tilemap":{"height":2,"tiles":[146,147,6,148],"width":2}},{"bounds":{"height":16,"x":0,"y":0,"width":16},"frame":85,"tilemap":{"height":2,"tiles":[149,0,150,151],"width":2}},{"bounds":{"height":16,"x":0,"y":0,"width":16},"frame":86,"tilemap":{"height":2,"tiles":[0,0,152,153],"width":2}},{"bounds":{"height":16,"x":0,"y":0,"width":16},"frame":87,"tilemap":{"height":2,"tiles":[0,0,154,155],"width":2}},{"bounds":{"height":16,"x":0,"y":0,"width":16},"frame":88,"tilemap":{"height":2,"tiles":[0,0,156,157],"width":2}},{"bounds":{"height":16,"x":0,"y":0,"width":16},"frame":89,"tilemap":{"height":2,"tiles":[0,0,158,159],"width":2}},{"bounds":{"height":16,"x":0,"y":0,"width":16},"frame":90,"tilemap":{"height":2,"tiles":[0,160,161,162],"width":2}},{"bounds":{"height":16,"x":0,"y":0,"width":16},"frame":91,"tilemap":{"height":2,"tiles":[163,164,165,4],"width":2}},{"bounds":{"height":16,"x":0,"y":0,"width":16},"frame":92,"tilemap":{"height":2,"tiles":[166,167,6,168],"width":2}},{"bounds":{"height":16,"x":0,"y":0,"width":16},"frame":93,"tilemap":{"height":2,"tiles":[169,170,171,172],"width":2}},{"bounds":{"height":16,"x":0,"y":0,"width":16},"frame":94,"tilemap":{"height":2,"tiles":[173,174,6,4],"width":2}},{"bounds":{"height":16,"x":0,"y":0,"width":16},"frame":95,"tilemap":{"height":2,"tiles":[175,176,6,4],"width":2}},{"bounds":{"height":16,"x":0,"y":0,"width":16},"frame":96,"tilemap":{"height":2,"tiles":[177,178,179,180],"width":2}},{"bounds":{"height":16,"x":0,"y":0,"width":16},"frame":97,"tilemap":{"height":2,"tiles":[181,182,183,184],"width":2}},{"bounds":{"height":16,"x":0,"y":0,"width":16},"frame":98,"tilemap":{"height":2,"tiles":[185,186,187,188],"width":2}},{"bounds":{"height":16,"x":0,"y":0,"width":16},"frame":99,"tilemap":{"height":2,"tiles":[0,0,189,0],"width":2}},{"bounds":{"height":16,"x":0,"y":0,"width":16},"frame":100,"tilemap":{"height":2,"tiles":[0,0,0,190],"width":2}},{"bounds":{"height":16,"x":0,"y":0,"width":16},"frame":101,"tilemap":{"height":2,"tiles":[191,192,193,194],"width":2}},{"bounds":{"height":16,"x":0,"y":0,"width":16},"frame":102,"tilemap":{"height":2,"tiles":[195,196,197,198],"width":2}},{"bounds":{"height":16,"x":0,"y":0,"width":16},"frame":103,"tilemap":{"height":2,"tiles":[199,200,201,202],"width":2}},{"bounds":{"height":16,"x":0,"y":0,"width":16},"frame":104,"tilemap":{"height":2,"tiles":[203,0,204,205],"width":2}},{"bounds":{"height":16,"x":0,"y":0,"width":16},"frame":105,"tilemap":{"height":2,"tiles":[0,206,207,208],"width":2}},{"bounds":{"height":16,"x":0,"y":0,"width":16},"frame":106,"tilemap":{"height":2,"tiles":[209,210,211,212],"width":2}},{"bounds":{"height":16,"x":0,"y":0,"width":16},"frame":107,"tilemap":{"height":2,"tiles":[213,214,215,216],"width":2}},{"bounds":{"height":16,"x":0,"y":0,"width":16},"frame":108,"tilemap":{"height":2,"tiles":[217,218,219,220],"width":2}},{"bounds":{"height":16,"x":0,"y":0,"width":16},"frame":109,"tilemap":{"height":2,"tiles":[0,0,221,0],"width":2}},{"bounds":{"height":16,"x":0,"y":0,"width":16},"frame":110,"tilemap":{"height":2,"tiles":[0,0,0,222],"width":2}},{"bounds":{"height":16,"x":0,"y":0,"width":16},"frame":111,"tilemap":{"height":2,"tiles":[223,224,225,226],"width":2}},{"bounds":{"height":16,"x":0,"y":0,"width":16},"frame":112,"tilemap":{"height":2,"tiles":[227,228,229,230],"width":2}},{"bounds":{"height":16,"x":0,"y":0,"width":16},"frame":113,"tilemap":{"height":2,"tiles":[231,232,233,234],"width":2}},{"bounds":{"height":16,"x":0,"y":0,"width":16},"frame":114,"tilemap":{"height":2,"tiles":[235,0,236,237],"width":2}},{"bounds":{"height":16,"x":0,"y":0,"width":16},"frame":115,"tilemap":{"height":2,"tiles":[0,0,238,239],"width":2}},{"bounds":{"height":16,"x":0,"y":0,"width":16},"frame":116,"tilemap":{"height":2,"tiles":[0,0,239,240],"width":2}},{"bounds":{"height":16,"x":0,"y":0,"width":16},"frame":117,"tilemap":{"height":2,"tiles":[0,241,242,243],"width":2}},{"bounds":{"height":16,"x":0,"y":0,"width":16},"frame":118,"tilemap":{"height":2,"tiles":[244,245,246,247],"width":2}},{"bounds":{"height":16,"x":0,"y":0,"width":16},"frame":119,"tilemap":{"height":2,"tiles":[248,249,250,251],"width":2}},{"bounds":{"height":16,"x":0,"y":0,"width":16},"frame":120,"tilemap":{"height":2,"tiles":[252,253,254,255],"width":2}},{"bounds":{"height":16,"x":0,"y":0,"width":16},"frame":121,"tilemap":{"height":2,"tiles":[13,14,256,257],"width":2}},{"bounds":{"height":16,"x":0,"y":0,"width":16},"frame":122,"tilemap":{"height":2,"tiles":[13,14,258,4],"width":2}},{"bounds":{"height":16,"x":0,"y":0,"width":16},"frame":123,"tilemap":{"height":2,"tiles":[13,14,6,259],"width":2}},{"bounds":{"height":16,"x":0,"y":0,"width":16},"frame":124,"tilemap":{"height":2,"tiles":[13,14,260,261],"width":2}},{"bounds":{"height":16,"x":0,"y":0,"width":16},"frame":125,"tilemap":{"height":2,"tiles":[262,263,0,0],"width":2}},{"bounds":{"height":16,"x":0,"y":0,"width":16},"frame":126,"tilemap":{"height":2,"tiles":[264,265,0,0],"width":2}},{"bounds":{"height":16,"x":0,"y":0,"width":16},"frame":127,"tilemap":{"height":2,"tiles":[266,267,268,269],"width":2}},{"bounds":{"height":16,"x":0,"y":0,"width":16},"frame":128,"tilemap":{"height":2,"tiles":[13,14,270,271],"width":2}},{"bounds":{"height":16,"x":0,"y":0,"width":16},"frame":129,"tilemap":{"height":2,"tiles":[13,14,272,273],"width":2}},{"bounds":{"height":16,"x":0,"y":0,"width":16},"frame":130,"tilemap":{"height":2,"tiles":[274,275,276,277],"width":2}},{"bounds":{"height":16,"x":0,"y":0,"width":16},"frame":131,"tilemap":{"height":2,"tiles":[278,279,0,0],"width":2}},{"bounds":{"height":16,"x":0,"y":0,"width":16},"frame":132,"tilemap":{"height":2,"tiles":[280,262,0,0],"width":2}},{"bounds":{"height":16,"x":0,"y":0,"width":16},"frame":133,"tilemap":{"height":2,"tiles":[281,282,0,283],"width":2}},{"bounds":{"height":16,"x":0,"y":0,"width":16},"frame":134,"tilemap":{"height":2,"tiles":[284,14,285,286],"width":2}},{"bounds":{"height":16,"x":0,"y":0,"width":16},"frame":135,"tilemap":{"height":2,"tiles":[13,287,288,289],"width":2}},{"bounds":{"height":16,"x":0,"y":0,"width":16},"frame":136,"tilemap":{"height":2,"tiles":[290,291,292,0],"width":2}},{"bounds":{"height":16,"x":0,"y":0,"width":16},"frame":137,"tilemap":{"height":2,"tiles":[5,293,6,4],"width":2}},{"bounds":{"height":16,"x":0,"y":0,"width":16},"frame":138,"tilemap":{"height":2,"tiles":[294,295,296,297],"width":2}},{"bounds":{"height":16,"x":0,"y":0,"width":16},"frame":139,"tilemap":{"height":2,"tiles":[0,0,298,299],"width":2}},{"bounds":{"height":16,"x":0,"y":0,"width":16},"frame":140,"tilemap":{"height":2,"tiles":[283,300,0,301],"width":2}},{"bounds":{"height":16,"x":0,"y":0,"width":16},"frame":141,"tilemap":{"height":2,"tiles":[302,14,303,4],"width":2}},{"bounds":{"height":16,"x":0,"y":0,"width":16},"frame":142,"tilemap":{"height":2,"tiles":[13,304,6,305],"width":2}},{"bounds":{"height":16,"x":0,"y":0,"width":16},"frame":143,"tilemap":{"height":2,"tiles":[306,292,307,0],"width":2}},{"bounds":{"height":16,"x":0,"y":0,"width":16},"frame":144,"tilemap":{"height":2,"tiles":[0,0,308,309],"width":2}},{"bounds":{"height":16,"x":0,"y":0,"width":16},"frame":145,"tilemap":{"height":2,"tiles":[310,311,312,313],"width":2}},{"bounds":{"height":16,"x":0,"y":0,"width":16},"frame":146,"tilemap":{"height":2,"tiles":[314,2,6,4],"width":2}},{"bounds":{"height":16,"x":0,"y":0,"width":16},"frame":147,"tilemap":{"height":2,"tiles":[315,316,6,317],"width":2}},{"bounds":{"height":16,"x":0,"y":0,"width":16},"frame":148,"tilemap":{"height":2,"tiles":[299,0,318,0],"width":2}},{"bounds":{"height":16,"x":0,"y":0,"width":16},"frame":149,"tilemap":{"height":2,"tiles":[319,320,321,322],"width":2}},{"bounds":{"height":16,"x":0,"y":0,"width":16},"frame":150,"tilemap":{"height":2,"tiles":[323,324,325,326],"width":2}},{"bounds":{"height":16,"x":0,"y":0,"width":16},"frame":151,"tilemap":{"height":2,"tiles":[0,308,0,327],"width":2}},{"bounds":{"height":16,"x":0,"y":0,"width":16},"frame":152,"tilemap":{"height":2,"tiles":[328,329,330,4],"width":2}},{"bounds":{"height":16,"x":0,"y":0,"width":16},"frame":153,"tilemap":{"height":2,"tiles":[331,332,333,334],"width":2}},{"bounds":{"height":16,"x":0,"y":0,"width":16},"frame":154,"tilemap":{"height":2,"tiles":[0,335,0,336],"width":2}},{"bounds":{"height":16,"x":0,"y":0,"width":16},"frame":155,"tilemap":{"height":2,"tiles":[13,14,337,4],"width":2}},{"bounds":{"height":16,"x":0,"y":0,"width":16},"frame":156,"tilemap":{"height":2,"tiles":[13,14,6,338],"width":2}},{"bounds":{"height":16,"x":0,"y":0,"width":16},"frame":157,"tilemap":{"height":2,"tiles":[339,0,340,0],"width":2}},{"bounds":{"height":16,"x":0,"y":0,"width":16},"frame":158,"tilemap":{"height":2,"tiles":[341,342,343,344],"width":2}},{"bounds":{"height":16,"x":0,"y":0,"width":16},"frame":159,"tilemap":{"height":2,"tiles":[13,345,6,346],"width":2}},{"bounds":{"height":16,"x":0,"y":0,"width":16},"frame":160,"tilemap":{"height":2,"tiles":[0,347,0,347],"width":2}},{"bounds":{"height":16,"x":0,"y":0,"width":16},"frame":161,"tilemap":{"height":2,"tiles":[348,14,349,4],"width":2}},{"bounds":{"height":16,"x":0,"y":0,"width":16},"frame":162,"tilemap":{"height":2,"tiles":[13,350,6,351],"width":2}},{"bounds":{"height":16,"x":0,"y":0,"width":16},"frame":163,"tilemap":{"height":2,"tiles":[352,0,352,0],"width":2}},{"bounds":{"height":16,"x":0,"y":0,"width":16},"frame":164,"tilemap":{"height":2,"tiles":[353,14,354,4],"width":2}},{"bounds":{"height":16,"x":0,"y":0,"width":16},"frame":165,"tilemap":{"height":2,"tiles":[355,356,357,358],"width":2}},{"bounds":{"height":16,"x":0,"y":0,"width":16},"frame":166,"tilemap":{"height":2,"tiles":[0,359,0,360],"width":2}},{"bounds":{"height":16,"x":0,"y":0,"width":16},"frame":167,"tilemap":{"height":2,"tiles":[361,0,362,0],"width":2}},{"bounds":{"height":16,"x":0,"y":0,"width":16},"frame":168,"tilemap":{"height":2,"tiles":[363,364,365,366],"width":2}},{"bounds":{"height":16,"x":0,"y":0,"width":16},"frame":169,"tilemap":{"height":2,"tiles":[13,367,272,368],"width":2}},{"bounds":{"height":16,"x":0,"y":0,"width":16},"frame":170,"tilemap":{"height":2,"tiles":[369,0,370,0],"width":2}},{"bounds":{"height":16,"x":0,"y":0,"width":16},"frame":171,"tilemap":{"height":2,"tiles":[371,372,373,374],"width":2}},{"bounds":{"height":16,"x":0,"y":0,"width":16},"frame":172,"tilemap":{"height":2,"tiles":[375,376,377,378],"width":2}},{"bounds":{"height":16,"x":0,"y":0,"width":16},"frame":173,"tilemap":{"height":2,"tiles":[0,379,0,380],"width":2}},{"bounds":{"height":16,"x":0,"y":0,"width":16},"frame":174,"tilemap":{"height":2,"tiles":[381,14,382,271],"width":2}},{"bounds":{"height":16,"x":0,"y":0,"width":16},"frame":175,"tilemap":{"height":2,"tiles":[13,14,6,383],"width":2}},{"bounds":{"height":16,"x":0,"y":0,"width":16},"frame":176,"tilemap":{"height":2,"tiles":[384,385,386,0],"width":2}},{"bounds":{"height":16,"x":0,"y":0,"width":16},"frame":177,"tilemap":{"height":2,"tiles":[0,387,388,389],"width":2}},{"bounds":{"height":16,"x":0,"y":0,"width":16},"frame":178,"tilemap":{"height":2,"tiles":[390,14,6,4],"width":2}},{"bounds":{"height":16,"x":0,"y":0,"width":16},"frame":179,"tilemap":{"height":2,"tiles":[13,391,6,4],"width":2}},{"bounds":{"height":16,"x":0,"y":0,"width":16},"frame":180,"tilemap":{"height":2,"tiles":[392,0,393,394],"width":2}},{"bounds":{"height":16,"x":0,"y":0,"width":16},"frame":181,"tilemap":{"height":2,"tiles":[395,396,0,397],"width":2}},{"bounds":{"height":16,"x":0,"y":0,"width":16},"frame":182,"tilemap":{"height":2,"tiles":[13,14,398,4],"width":2}},{"bounds":{"height":16,"x":0,"y":0,"width":16},"frame":183,"tilemap":{"height":2,"tiles":[328,78,330,4],"width":2}},{"bounds":{"height":16,"x":0,"y":0,"width":16},"frame":184,"tilemap":{"height":2,"tiles":[67,316,6,317],"width":2}},{"bounds":{"height":16,"x":0,"y":0,"width":16},"frame":185,"tilemap":{"height":2,"tiles":[13,399,6,4],"width":2}},{"bounds":{"height":16,"x":0,"y":0,"width":16},"frame":186,"tilemap":{"height":2,"tiles":[400,14,6,4],"width":2}},{"bounds":{"height":16,"x":0,"y":0,"width":16},"frame":187,"tilemap":{"height":2,"tiles":[381,14,382,401],"width":2}},{"bounds":{"height":16,"x":0,"y":0,"width":16},"frame":188,"tilemap":{"height":2,"tiles":[13,367,402,368],"width":2}},{"bounds":{"height":16,"x":0,"y":0,"width":16},"frame":189,"tilemap":{"height":2,"tiles":[13,403,6,66],"width":2}},{"bounds":{"height":16,"x":0,"y":0,"width":16},"frame":190,"tilemap":{"height":2,"tiles":[404,0,405,186],"width":2}},{"bounds":{"height":16,"x":0,"y":0,"width":16},"frame":191,"tilemap":{"height":2,"tiles":[380,406,0,0],"width":2}},{"bounds":{"height":16,"x":0,"y":0,"width":16},"frame":192,"tilemap":{"height":2,"tiles":[407,408,409,410],"width":2}},{"bounds":{"height":16,"x":0,"y":0,"width":16},"frame":193,"tilemap":{"height":2,"tiles":[13,14,411,26],"width":2}},{"bounds":{"height":16,"x":0,"y":0,"width":16},"frame":194,"tilemap":{"height":2,"tiles":[13,14,27,412],"width":2}},{"bounds":{"height":16,"x":0,"y":0,"width":16},"frame":195,"tilemap":{"height":2,"tiles":[413,414,415,416],"width":2}},{"bounds":{"height":16,"x":0,"y":0,"width":16},"frame":196,"tilemap":{"height":2,"tiles":[417,370,0,0],"width":2}},{"bounds":{"height":16,"x":0,"y":0,"width":16},"frame":197,"tilemap":{"height":2,"tiles":[0,418,191,419],"width":2}},{"bounds":{"height":16,"x":0,"y":0,"width":16},"frame":198,"tilemap":{"height":2,"tiles":[420,14,74,4],"width":2}},{"bounds":{"height":16,"x":0,"y":0,"width":16},"frame":199,"tilemap":{"height":2,"tiles":[421,422,6,423],"width":2}},{"bounds":{"height":16,"x":0,"y":0,"width":16},"frame":200,"tilemap":{"height":2,"tiles":[186,0,424,425],"width":2}},{"bounds":{"height":16,"x":0,"y":0,"width":16},"frame":201,"tilemap":{"height":2,"tiles":[0,191,426,427],"width":2}},{"bounds":{"height":16,"x":0,"y":0,"width":16},"frame":202,"tilemap":{"height":2,"tiles":[428,429,430,4],"width":2}},{"bounds":{"height":16,"x":0,"y":0,"width":16},"frame":203,"tilemap":{"height":2,"tiles":[67,431,6,4],"width":2}},{"bounds":{"height":16,"x":0,"y":0,"width":16},"frame":204,"tilemap":{"height":2,"tiles":[432,433,434,435],"width":2}},{"bounds":{"height":16,"x":0,"y":0,"width":16},"frame":205,"tilemap":{"height":2,"tiles":[0,0,436,437],"width":2}},{"bounds":{"height":16,"x":0,"y":0,"width":16},"frame":206,"tilemap":{"height":2,"tiles":[0,0,438,439],"width":2}},{"bounds":{"height":16,"x":0,"y":0,"width":16},"frame":207,"tilemap":{"height":2,"tiles":[0,0,439,440],"width":2}},{"bounds":{"height":16,"x":0,"y":0,"width":16},"frame":208,"tilemap":{"height":2,"tiles":[0,0,441,442],"width":2}},{"bounds":{"height":16,"x":0,"y":0,"width":16},"frame":209,"tilemap":{"height":2,"tiles":[443,444,445,446],"width":2}},{"bounds":{"height":16,"x":0,"y":0,"width":16},"frame":210,"tilemap":{"height":2,"tiles":[447,78,6,4],"width":2}},{"bounds":{"height":16,"x":0,"y":0,"width":16},"frame":211,"tilemap":{"height":2,"tiles":[13,448,6,4],"width":2}},{"bounds":{"height":16,"x":0,"y":0,"width":16},"frame":212,"tilemap":{"height":2,"tiles":[449,70,6,4],"width":2}},{"bounds":{"height":16,"x":0,"y":0,"width":16},"frame":213,"tilemap":{"height":2,"tiles":[75,450,6,4],"width":2}},{"bounds":{"height":16,"x":0,"y":0,"width":16},"frame":214,"tilemap":{"height":2,"tiles":[451,14,6,4],"width":2}},{"bounds":{"height":16,"x":0,"y":0,"width":16},"frame":215,"tilemap":{"height":2,"tiles":[13,14,452,261],"width":2}},{"bounds":{"height":16,"x":0,"y":0,"width":16},"frame":216,"tilemap":{"height":2,"tiles":[13,14,256,453],"width":2}},{"bounds":{"height":16,"x":0,"y":0,"width":16},"frame":217,"tilemap":{"height":2,"tiles":[13,454,455,456],"width":2}},{"bounds":{"height":16,"x":0,"y":0,"width":16},"frame":218,"tilemap":{"height":2,"tiles":[457,458,459,0],"width":2}},{"bounds":{"height":16,"x":0,"y":0,"width":16},"frame":219,"tilemap":{"height":2,"tiles":[460,262,0,0],"width":2}},{"bounds":{"height":16,"x":0,"y":0,"width":16},"frame":220,"tilemap":{"height":2,"tiles":[262,461,0,0],"width":2}},{"bounds":{"height":16,"x":0,"y":0,"width":16},"frame":221,"tilemap":{"height":2,"tiles":[462,463,0,464],"width":2}},{"bounds":{"height":16,"x":0,"y":0,"width":16},"frame":222,"tilemap":{"height":2,"tiles":[465,14,466,467],"width":2}},{"bounds":{"height":16,"x":0,"y":0,"width":16},"frame":223,"tilemap":{"height":2,"tiles":[13,468,469,470],"width":2}},{"bounds":{"height":16,"x":0,"y":0,"width":16},"frame":224,"tilemap":{"height":2,"tiles":[471,0,0,0],"width":2}},{"bounds":{"height":16,"x":0,"y":0,"width":16},"frame":225,"tilemap":{"height":2,"tiles":[0,472,0,0],"width":2}},{"bounds":{"height":16,"x":0,"y":0,"width":16},"frame":226,"tilemap":{"height":2,"tiles":[473,14,474,475],"width":2}},{"bounds":{"height":16,"x":0,"y":0,"width":16},"frame":227,"tilemap":{"height":2,"tiles":[13,476,477,478],"width":2}},{"bounds":{"height":16,"x":0,"y":0,"width":16},"frame":228,"tilemap":{"height":2,"tiles":[479,0,0,0],"width":2}},{"bounds":{"height":16,"x":0,"y":0,"width":16},"frame":229,"tilemap":{"height":2,"tiles":[0,480,0,0],"width":2}},{"bounds":{"height":16,"x":0,"y":0,"width":16},"frame":230,"tilemap":{"height":2,"tiles":[481,14,482,483],"width":2}},{"bounds":{"height":16,"x":0,"y":0,"width":16},"frame":231,"tilemap":{"height":2,"tiles":[484,485,486,0],"width":2}},{"bounds":{"height":16,"x":0,"y":0,"width":16},"frame":232,"tilemap":{"height":2,"tiles":[487,488,0,489],"width":2}},{"bounds":{"height":16,"x":0,"y":0,"width":16},"frame":233,"tilemap":{"height":2,"tiles":[13,490,6,491],"width":2}},{"bounds":{"height":16,"x":0,"y":0,"width":16},"frame":234,"tilemap":{"height":2,"tiles":[492,0,493,0],"width":2}},{"bounds":{"height":16,"x":0,"y":0,"width":16},"frame":235,"tilemap":{"height":2,"tiles":[0,494,0,495],"width":2}},{"bounds":{"height":16,"x":0,"y":0,"width":16},"frame":236,"tilemap":{"height":2,"tiles":[496,14,497,4],"width":2}},{"bounds":{"height":16,"x":0,"y":0,"width":16},"frame":237,"tilemap":{"height":2,"tiles":[13,63,6,498],"width":2}},{"bounds":{"height":16,"x":0,"y":0,"width":16},"frame":238,"tilemap":{"height":2,"tiles":[493,0,499,0],"width":2}},{"bounds":{"height":16,"x":0,"y":0,"width":16},"frame":239,"tilemap":{"height":2,"tiles":[0,495,0,500],"width":2}},{"bounds":{"height":16,"x":0,"y":0,"width":16},"frame":240,"tilemap":{"height":2,"tiles":[71,14,501,4],"width":2}},{"bounds":{"height":16,"x":0,"y":0,"width":16},"frame":241,"tilemap":{"height":2,"tiles":[502,0,503,504],"width":2}},{"bounds":{"height":16,"x":0,"y":0,"width":16},"frame":242,"tilemap":{"height":2,"tiles":[0,505,506,507],"width":2}},{"bounds":{"height":16,"x":0,"y":0,"width":16},"frame":243,"tilemap":{"height":2,"tiles":[508,509,6,510],"width":2}},{"bounds":{"height":16,"x":0,"y":0,"width":16},"frame":244,"tilemap":{"height":2,"tiles":[0,0,511,0],"width":2}},{"bounds":{"height":16,"x":0,"y":0,"width":16},"frame":245,"tilemap":{"height":2,"tiles":[0,0,0,512],"width":2}},{"bounds":{"height":16,"x":0,"y":0,"width":16},"frame":246,"tilemap":{"height":2,"tiles":[513,514,515,4],"width":2}},{"bounds":{"height":16,"x":0,"y":0,"width":16},"frame":247,"tilemap":{"height":2,"tiles":[516,517,6,518],"width":2}},{"bounds":{"height":16,"x":0,"y":0,"width":16},"frame":248,"tilemap":{"height":2,"tiles":[0,0,519,0],"width":2}},{"bounds":{"height":16,"x":0,"y":0,"width":16},"frame":249,"tilemap":{"height":2,"tiles":[0,0,0,520],"width":2}},{"bounds":{"height":16,"x":0,"y":0,"width":16},"frame":250,"tilemap":{"height":2,"tiles":[521,522,523,4],"width":2}},{"bounds":{"height":16,"x":0,"y":0,"width":16},"frame":251,"tilemap":{"height":2,"tiles":[524,525,6,526],"width":2}},{"bounds":{"height":16,"x":0,"y":0,"width":16},"frame":252,"tilemap":{"height":2,"tiles":[527,0,528,529],"width":2}},{"bounds":{"height":16,"x":0,"y":0,"width":16},"frame":253,"tilemap":{"height":2,"tiles":[0,0,530,439],"width":2}},{"bounds":{"height":16,"x":0,"y":0,"width":16},"frame":254,"tilemap":{"height":2,"tiles":[0,0,439,531],"width":2}},{"bounds":{"height":16,"x":0,"y":0,"width":16},"frame":255,"tilemap":{"height":2,"tiles":[0,532,533,534],"width":2}},{"bounds":{"height":16,"x":0,"y":0,"width":16},"frame":256,"tilemap":{"height":2,"tiles":[535,536,537,4],"width":2}},{"bounds":{"height":16,"x":0,"y":0,"width":16},"frame":257,"tilemap":{"height":2,"tiles":[538,70,6,4],"width":2}},{"bounds":{"height":16,"x":0,"y":0,"width":16},"frame":258,"tilemap":{"height":2,"tiles":[75,539,6,4],"width":2}},{"bounds":{"height":16,"x":0,"y":0,"width":16},"frame":259,"tilemap":{"height":2,"tiles":[0,0,0,540],"width":2}},{"bounds":{"height":16,"x":0,"y":0,"width":16},"frame":260,"tilemap":{"height":2,"tiles":[443,541,542,543],"width":2}},{"bounds":{"height":16,"x":0,"y":0,"width":16},"frame":261,"tilemap":{"height":2,"tiles":[544,545,6,4],"width":2}},{"bounds":{"height":16,"x":0,"y":0,"width":16},"frame":262,"tilemap":{"height":2,"tiles":[546,547,6,4],"width":2}},{"bounds":{"height":16,"x":0,"y":0,"width":16},"frame":263,"tilemap":{"height":2,"tiles":[548,433,549,550],"width":2}},{"bounds":{"height":16,"x":0,"y":0,"width":16},"frame":264,"tilemap":{"height":2,"tiles":[0,0,551,0],"width":2}},{"bounds":{"height":16,"x":0,"y":0,"width":16},"frame":265,"tilemap":{"height":2,"tiles":[0,443,371,552],"width":2}},{"bounds":{"height":16,"x":0,"y":0,"width":16},"frame":266,"tilemap":{"height":2,"tiles":[553,554,537,4],"width":2}},{"bounds":{"height":16,"x":0,"y":0,"width":16},"frame":267,"tilemap":{"height":2,"tiles":[555,556,6,526],"width":2}},{"bounds":{"height":16,"x":0,"y":0,"width":16},"frame":268,"tilemap":{"height":2,"tiles":[433,0,557,376],"width":2}},{"bounds":{"height":16,"x":0,"y":0,"width":16},"frame":269,"tilemap":{"height":2,"tiles":[0,0,0,558],"width":2}},{"bounds":{"height":16,"x":0,"y":0,"width":16},"frame":270,"tilemap":{"height":2,"tiles":[559,514,560,4],"width":2}},{"bounds":{"height":16,"x":0,"y":0,"width":16},"frame":271,"tilemap":{"height":2,"tiles":[508,561,6,562],"width":2}},{"bounds":{"height":16,"x":0,"y":0,"width":16},"frame":272,"tilemap":{"height":2,"tiles":[0,0,563,0],"width":2}},{"bounds":{"height":16,"x":0,"y":0,"width":16},"frame":273,"tilemap":{"height":2,"tiles":[371,564,565,566],"width":2}},{"bounds":{"height":16,"x":0,"y":0,"width":16},"frame":274,"tilemap":{"height":2,"tiles":[567,376,568,569],"width":2}},{"bounds":{"height":16,"x":0,"y":0,"width":16},"frame":275,"tilemap":{"height":2,"tiles":[570,14,571,4],"width":2}},{"bounds":{"height":16,"x":0,"y":0,"width":16},"frame":276,"tilemap":{"height":2,"tiles":[13,572,6,573],"width":2}},{"bounds":{"height":16,"x":0,"y":0,"width":16},"frame":277,"tilemap":{"height":2,"tiles":[574,14,575,4],"width":2}},{"bounds":{"height":16,"x":0,"y":0,"width":16},"frame":278,"tilemap":{"height":2,"tiles":[13,576,6,577],"width":2}},{"bounds":{"height":16,"x":0,"y":0,"width":16},"frame":279,"tilemap":{"height":2,"tiles":[578,579,321,580],"width":2}},{"bounds":{"height":16,"x":0,"y":0,"width":16},"frame":280,"tilemap":{"height":2,"tiles":[581,582,583,326],"width":2}},{"bounds":{"height":16,"x":0,"y":0,"width":16},"frame":281,"tilemap":{"height":2,"tiles":[0,584,0,0],"width":2}},{"bounds":{"height":16,"x":0,"y":0,"width":16},"frame":282,"tilemap":{"height":2,"tiles":[585,14,586,483],"width":2}},{"bounds":{"height":16,"x":0,"y":0,"width":16},"frame":283,"tilemap":{"height":2,"tiles":[13,587,477,588],"width":2}},{"bounds":{"height":16,"x":0,"y":0,"width":16},"frame":284,"tilemap":{"height":2,"tiles":[589,0,0,0],"width":2}},{"bounds":{"height":16,"x":0,"y":0,"width":16},"frame":285,"tilemap":{"height":2,"tiles":[321,590,0,268],"width":2}},{"bounds":{"height":16,"x":0,"y":0,"width":16},"frame":286,"tilemap":{"height":2,"tiles":[465,14,591,592],"width":2}},{"bounds":{"height":16,"x":0,"y":0,"width":16},"frame":287,"tilemap":{"height":2,"tiles":[13,454,593,594],"width":2}},{"bounds":{"height":16,"x":0,"y":0,"width":16},"frame":288,"tilemap":{"height":2,"tiles":[595,326,277,0],"width":2}},{"bounds":{"height":16,"x":0,"y":0,"width":16},"frame":289,"tilemap":{"height":2,"tiles":[0,596,0,0],"width":2}},{"bounds":{"height":16,"x":0,"y":0,"width":16},"frame":290,"tilemap":{"height":2,"tiles":[597,598,268,599],"width":2}},{"bounds":{"height":16,"x":0,"y":0,"width":16},"frame":291,"tilemap":{"height":2,"tiles":[13,14,600,601],"width":2}},{"bounds":{"height":16,"x":0,"y":0,"width":16},"frame":292,"tilemap":{"height":2,"tiles":[13,14,602,603],"width":2}},{"bounds":{"height":16,"x":0,"y":0,"width":16},"frame":293,"tilemap":{"height":2,"tiles":[604,605,606,277],"width":2}},{"bounds":{"height":16,"x":0,"y":0,"width":16},"frame":294,"tilemap":{"height":2,"tiles":[607,0,0,0],"width":2}},{"bounds":{"height":16,"x":0,"y":0,"width":16},"frame":295,"tilemap":{"height":2,"tiles":[608,609,610,611],"width":2}},{"bounds":{"height":16,"x":0,"y":0,"width":16},"frame":296,"tilemap":{"height":2,"tiles":[608,609,610,612],"width":2}},{"bounds":{"height":16,"x":0,"y":0,"width":16},"frame":297,"tilemap":{"height":2,"tiles":[608,613,614,615],"width":2}},{"bounds":{"height":16,"x":0,"y":0,"width":16},"frame":298,"tilemap":{"height":2,"tiles":[616,617,618,0],"width":2}},{"bounds":{"height":16,"x":0,"y":0,"width":16},"frame":299,"tilemap":{"height":2,"tiles":[619,620,0,0],"width":2}},{"bounds":{"height":16,"x":0,"y":0,"width":16},"frame":300,"tilemap":{"height":2,"tiles":[621,622,0,0],"width":2}},{"bounds":{"height":16,"x":0,"y":0,"width":16},"frame":301,"tilemap":{"height":2,"tiles":[622,623,0,0],"width":2}},{"bounds":{"height":16,"x":0,"y":0,"width":16},"frame":302,"tilemap":{"height":2,"tiles":[624,625,0,0],"width":2}},{"bounds":{"height":16,"x":0,"y":0,"width":16},"frame":303,"tilemap":{"height":2,"tiles":[626,627,0,628],"width":2}},{"bounds":{"height":16,"x":0,"y":0,"width":16},"frame":304,"tilemap":{"height":2,"tiles":[629,609,630,631],"width":2}},{"bounds":{"height":16,"x":0,"y":0,"width":16},"frame":305,"tilemap":{"height":2,"tiles":[608,609,632,611],"width":2}},{"bounds":{"height":16,"x":0,"y":0,"width":16},"frame":306,"tilemap":{"height":2,"tiles":[608,609,610,633],"width":2}},{"bounds":{"height":16,"x":0,"y":0,"width":16},"frame":307,"tilemap":{"height":2,"tiles":[634,635,636,0],"width":2}},{"bounds":{"height":16,"x":0,"y":0,"width":16},"frame":308,"tilemap":{"height":2,"tiles":[637,0,0,0],"width":2}},{"bounds":{"height":16,"x":0,"y":0,"width":16},"frame":309,"tilemap":{"height":2,"tiles":[0,638,0,0],"width":2}},{"bounds":{"height":16,"x":0,"y":0,"width":16},"frame":310,"tilemap":{"height":2,"tiles":[639,640,0,641],"width":2}},{"bounds":{"height":16,"x":0,"y":0,"width":16},"frame":311,"tilemap":{"height":2,"tiles":[608,609,642,611],"width":2}},{"bounds":{"height":16,"x":0,"y":0,"width":16},"frame":312,"tilemap":{"height":2,"tiles":[643,644,645,0],"width":2}},{"bounds":{"height":16,"x":0,"y":0,"width":16},"frame":313,"tilemap":{"height":2,"tiles":[646,647,0,648],"width":2}},{"bounds":{"height":16,"x":0,"y":0,"width":16},"frame":314,"tilemap":{"height":2,"tiles":[649,650,651,0],"width":2}},{"bounds":{"height":16,"x":0,"y":0,"width":16},"frame":315,"tilemap":{"height":2,"tiles":[652,653,0,654],"width":2}},{"bounds":{"height":16,"x":0,"y":0,"width":16},"frame":316,"tilemap":{"height":2,"tiles":[655,0,656,657],"width":2}},{"bounds":{"height":16,"x":0,"y":0,"width":16},"frame":317,"tilemap":{"height":2,"tiles":[0,658,659,660],"width":2}},{"bounds":{"height":16,"x":0,"y":0,"width":16},"frame":318,"tilemap":{"height":2,"tiles":[608,661,610,611],"width":2}},{"bounds":{"height":16,"x":0,"y":0,"width":16},"frame":319,"tilemap":{"height":2,"tiles":[662,0,663,664],"width":2}},{"bounds":{"height":16,"x":0,"y":0,"width":16},"frame":320,"tilemap":{"height":2,"tiles":[0,665,666,667],"width":2}},{"bounds":{"height":16,"x":0,"y":0,"width":16},"frame":321,"tilemap":{"height":2,"tiles":[668,609,610,611],"width":2}},{"bounds":{"height":16,"x":0,"y":0,"width":16},"frame":322,"tilemap":{"height":2,"tiles":[669,0,670,671],"width":2}},{"bounds":{"height":16,"x":0,"y":0,"width":16},"frame":323,"tilemap":{"height":2,"tiles":[0,0,672,0],"width":2}},{"bounds":{"height":16,"x":0,"y":0,"width":16},"frame":324,"tilemap":{"height":2,"tiles":[0,0,0,673],"width":2}},{"bounds":{"height":16,"x":0,"y":0,"width":16},"frame":325,"tilemap":{"height":2,"tiles":[0,674,675,676],"width":2}},{"bounds":{"height":16,"x":0,"y":0,"width":16},"frame":326,"tilemap":{"height":2,"tiles":[608,677,610,611],"width":2}},{"bounds":{"height":16,"x":0,"y":0,"width":16},"frame":327,"tilemap":{"height":2,"tiles":[678,679,610,680],"width":2}},{"bounds":{"height":16,"x":0,"y":0,"width":16},"frame":328,"tilemap":{"height":2,"tiles":[681,0,682,683],"width":2}},{"bounds":{"height":16,"x":0,"y":0,"width":16},"frame":329,"tilemap":{"height":2,"tiles":[0,0,684,685],"width":2}},{"bounds":{"height":16,"x":0,"y":0,"width":16},"frame":330,"tilemap":{"height":2,"tiles":[0,0,686,687],"width":2}},{"bounds":{"height":16,"x":0,"y":0,"width":16},"frame":331,"tilemap":{"height":2,"tiles":[0,0,687,688],"width":2}},{"bounds":{"height":16,"x":0,"y":0,"width":16},"frame":332,"tilemap":{"height":2,"tiles":[0,0,689,690],"width":2}},{"bounds":{"height":16,"x":0,"y":0,"width":16},"frame":333,"tilemap":{"height":2,"tiles":[0,691,692,693],"width":2}},{"bounds":{"height":16,"x":0,"y":0,"width":16},"frame":334,"tilemap":{"height":2,"tiles":[694,695,696,611],"width":2}},{"bounds":{"height":16,"x":0,"y":0,"width":16},"frame":335,"tilemap":{"height":2,"tiles":[697,609,610,611],"width":2}},{"bounds":{"height":16,"x":0,"y":0,"width":16},"frame":336,"tilemap":{"height":2,"tiles":[608,698,699,700],"width":2}},{"bounds":{"height":16,"x":0,"y":0,"width":16},"frame":337,"tilemap":{"height":2,"tiles":[701,0,0,0],"width":2}},{"bounds":{"height":16,"x":0,"y":0,"width":16},"frame":338,"tilemap":{"height":2,"tiles":[0,702,0,0],"width":2}},{"bounds":{"height":16,"x":0,"y":0,"width":16},"frame":339,"tilemap":{"height":2,"tiles":[703,609,704,705],"width":2}},{"bounds":{"height":16,"x":0,"y":0,"width":16},"frame":340,"tilemap":{"height":2,"tiles":[706,707,708,0],"width":2}},{"bounds":{"height":16,"x":0,"y":0,"width":16},"frame":341,"tilemap":{"height":2,"tiles":[709,710,0,711],"width":2}},{"bounds":{"height":16,"x":0,"y":0,"width":16},"frame":342,"tilemap":{"height":2,"tiles":[712,0,713,0],"width":2}},{"bounds":{"height":16,"x":0,"y":0,"width":16},"frame":343,"tilemap":{"height":2,"tiles":[0,714,0,715],"width":2}},{"bounds":{"height":16,"x":0,"y":0,"width":16},"frame":344,"tilemap":{"height":2,"tiles":[716,0,717,0],"width":2}},{"bounds":{"height":16,"x":0,"y":0,"width":16},"frame":345,"tilemap":{"height":2,"tiles":[0,718,0,719],"width":2}},{"bounds":{"height":16,"x":0,"y":0,"width":16},"frame":346,"tilemap":{"height":2,"tiles":[717,0,720,0],"width":2}},{"bounds":{"height":16,"x":0,"y":0,"width":16},"frame":347,"tilemap":{"height":2,"tiles":[0,719,0,721],"width":2}},{"bounds":{"height":16,"x":0,"y":0,"width":16},"frame":348,"tilemap":{"height":2,"tiles":[722,0,723,0],"width":2}},{"bounds":{"height":16,"x":0,"y":0,"width":16},"frame":349,"tilemap":{"height":2,"tiles":[0,724,0,725],"width":2}},{"bounds":{"height":16,"x":0,"y":0,"width":16},"frame":350,"tilemap":{"height":2,"tiles":[726,0,727,728],"width":2}},{"bounds":{"height":16,"x":0,"y":0,"width":16},"frame":351,"tilemap":{"height":2,"tiles":[0,729,730,731],"width":2}},{"bounds":{"height":16,"x":0,"y":0,"width":16},"frame":352,"tilemap":{"height":2,"tiles":[732,733,610,734],"width":2}},{"bounds":{"height":16,"x":0,"y":0,"width":16},"frame":353,"tilemap":{"height":2,"tiles":[0,0,735,0],"width":2}},{"bounds":{"height":16,"x":0,"y":0,"width":16},"frame":354,"tilemap":{"height":2,"tiles":[0,0,0,736],"width":2}},{"bounds":{"height":16,"x":0,"y":0,"width":16},"frame":355,"tilemap":{"height":2,"tiles":[737,738,739,611],"width":2}},{"bounds":{"height":16,"x":0,"y":0,"width":16},"frame":356,"tilemap":{"height":2,"tiles":[740,741,742,743],"width":2}},{"bounds":{"height":16,"x":0,"y":0,"width":16},"frame":357,"tilemap":{"height":2,"tiles":[13,14,744,745],"width":2}},{"bounds":{"height":16,"x":0,"y":0,"width":16},"frame":358,"tilemap":{"height":2,"tiles":[13,14,746,747],"width":2}},{"bounds":{"height":16,"x":0,"y":0,"width":16},"frame":359,"tilemap":{"height":2,"tiles":[748,749,750,751],"width":2}},{"bounds":{"height":16,"x":0,"y":0,"width":16},"frame":360,"tilemap":{"height":2,"tiles":[752,14,753,754],"width":2}},{"bounds":{"height":16,"x":0,"y":0,"width":16},"frame":361,"tilemap":{"height":2,"tiles":[13,755,756,757],"width":2}},{"bounds":{"height":16,"x":0,"y":0,"width":16},"frame":362,"tilemap":{"height":2,"tiles":[758,759,760,0],"width":2}},{"bounds":{"height":16,"x":0,"y":0,"width":16},"frame":363,"tilemap":{"height":2,"tiles":[761,762,0,0],"width":2}},{"bounds":{"height":16,"x":0,"y":0,"width":16},"frame":364,"tilemap":{"height":2,"tiles":[763,764,0,0],"width":2}},{"bounds":{"height":16,"x":0,"y":0,"width":16},"frame":365,"tilemap":{"height":2,"tiles":[765,766,0,0],"width":2}},{"bounds":{"height":16,"x":0,"y":0,"width":16},"frame":366,"tilemap":{"height":2,"tiles":[767,768,0,0],"width":2}},{"bounds":{"height":16,"x":0,"y":0,"width":16},"frame":367,"tilemap":{"height":2,"tiles":[769,770,0,771],"width":2}},{"bounds":{"height":16,"x":0,"y":0,"width":16},"frame":368,"tilemap":{"height":2,"tiles":[772,14,773,774],"width":2}},{"bounds":{"height":16,"x":0,"y":0,"width":16},"frame":369,"tilemap":{"height":2,"tiles":[13,775,776,777],"width":2}},{"bounds":{"height":16,"x":0,"y":0,"width":16},"frame":370,"tilemap":{"height":2,"tiles":[778,14,779,780],"width":2}},{"bounds":{"height":16,"x":0,"y":0,"width":16},"frame":371,"tilemap":{"height":2,"tiles":[781,782,783,784],"width":2}},{"bounds":{"height":16,"x":0,"y":0,"width":16},"frame":372,"tilemap":{"height":2,"tiles":[785,786,787,0],"width":2}},{"bounds":{"height":16,"x":0,"y":0,"width":16},"frame":373,"tilemap":{"height":2,"tiles":[788,789,0,0],"width":2}},{"bounds":{"height":16,"x":0,"y":0,"width":16},"frame":374,"tilemap":{"height":2,"tiles":[790,791,0,0],"width":2}},{"bounds":{"height":16,"x":0,"y":0,"width":16},"frame":375,"tilemap":{"height":2,"tiles":[792,793,0,794],"width":2}},{"bounds":{"height":16,"x":0,"y":0,"width":16},"frame":376,"tilemap":{"height":2,"tiles":[795,796,797,798],"width":2}},{"bounds":{"height":16,"x":0,"y":0,"width":16},"frame":377,"tilemap":{"height":2,"tiles":[13,799,800,801],"width":2}},{"bounds":{"height":16,"x":0,"y":0,"width":16},"frame":378,"tilemap":{"height":2,"tiles":[802,803,804,805],"width":2}},{"bounds":{"height":16,"x":0,"y":0,"width":16},"frame":379,"tilemap":{"height":2,"tiles":[806,807,808,809],"width":2}},{"bounds":{"height":16,"x":0,"y":0,"width":16},"frame":380,"tilemap":{"height":2,"tiles":[810,811,812,813],"width":2}},{"bounds":{"height":16,"x":0,"y":0,"width":16},"frame":381,"tilemap":{"height":2,"tiles":[814,815,816,0],"width":2}},{"bounds":{"height":16,"x":0,"y":0,"width":16},"frame":382,"tilemap":{"height":2,"tiles":[817,818,0,0],"width":2}},{"bounds":{"height":16,"x":0,"y":0,"width":16},"frame":383,"tilemap":{"height":2,"tiles":[818,819,0,0],"width":2}},{"bounds":{"height":16,"x":0,"y":0,"width":16},"frame":384,"tilemap":{"height":2,"tiles":[820,821,0,822],"width":2}},{"bounds":{"height":16,"x":0,"y":0,"width":16},"frame":385,"tilemap":{"height":2,"tiles":[823,824,825,826],"width":2}},{"bounds":{"height":16,"x":0,"y":0,"width":16},"frame":386,"tilemap":{"height":2,"tiles":[827,828,829,830],"width":2}},{"bounds":{"height":16,"x":0,"y":0,"width":16},"frame":387,"tilemap":{"height":2,"tiles":[831,832,833,834],"width":2}},{"bounds":{"height":16,"x":0,"y":0,"width":16},"frame":388,"tilemap":{"height":2,"tiles":[835,0,0,0],"width":2}},{"bounds":{"height":16,"x":0,"y":0,"width":16},"frame":389,"tilemap":{"height":2,"tiles":[0,836,0,0],"width":2}},{"bounds":{"height":16,"x":0,"y":0,"width":16},"frame":390,"tilemap":{"height":2,"tiles":[837,838,839,840],"width":2}},{"bounds":{"height":16,"x":0,"y":0,"width":16},"frame":391,"tilemap":{"height":2,"tiles":[841,842,843,844],"width":2}},{"bounds":{"height":16,"x":0,"y":0,"width":16},"frame":392,"tilemap":{"height":2,"tiles":[845,846,847,848],"width":2}},{"bounds":{"height":16,"x":0,"y":0,"width":16},"frame":393,"tilemap":{"height":2,"tiles":[849,850,851,0],"width":2}},{"bounds":{"height":16,"x":0,"y":0,"width":16},"frame":394,"tilemap":{"height":2,"tiles":[852,853,0,854],"width":2}},{"bounds":{"height":16,"x":0,"y":0,"width":16},"frame":395,"tilemap":{"height":2,"tiles":[855,856,857,858],"width":2}},{"bounds":{"height":16,"x":0,"y":0,"width":16},"frame":396,"tilemap":{"height":2,"tiles":[859,860,861,862],"width":2}},{"bounds":{"height":16,"x":0,"y":0,"width":16},"frame":397,"tilemap":{"height":2,"tiles":[863,864,865,292],"width":2}},{"bounds":{"height":16,"x":0,"y":0,"width":16},"frame":398,"tilemap":{"height":2,"tiles":[866,0,0,0],"width":2}},{"bounds":{"height":16,"x":0,"y":0,"width":16},"frame":399,"tilemap":{"height":2,"tiles":[0,867,0,0],"width":2}},{"bounds":{"height":16,"x":0,"y":0,"width":16},"frame":400,"tilemap":{"height":2,"tiles":[868,869,283,870],"width":2}},{"bounds":{"height":16,"x":0,"y":0,"width":16},"frame":401,"tilemap":{"height":2,"tiles":[871,872,873,874],"width":2}},{"bounds":{"height":16,"x":0,"y":0,"width":16},"frame":402,"tilemap":{"height":2,"tiles":[0,0,0,0],"width":2}},{"bounds":{"height":16,"x":0,"y":0,"width":16},"frame":403,"tilemap":{"height":2,"tiles":[0,0,0,0],"width":2}},{"bounds":{"height":16,"x":0,"y":0,"width":16},"frame":404,"tilemap":{"height":2,"tiles":[0,0,0,0],"width":2}},{"bounds":{"height":16,"x":0,"y":0,"width":16},"frame":405,"tilemap":{"height":2,"tiles":[0,0,0,0],"width":2}},{"bounds":{"height":16,"x":0,"y":0,"width":16},"frame":406,"tilemap":{"height":2,"tiles":[0,0,0,0],"width":2}},{"bounds":{"height":16,"x":0,"y":0,"width":16},"frame":407,"tilemap":{"height":2,"tiles":[0,0,0,0],"width":2}},{"bounds":{"height":16,"x":0,"y":0,"width":16},"frame":408,"tilemap":{"height":2,"tiles":[0,0,0,0],"width":2}},{"bounds":{"height":16,"x":0,"y":0,"width":16},"frame":409,"tilemap":{"height":2,"tiles":[0,0,0,0],"width":2}},{"bounds":{"height":16,"x":0,"y":0,"width":16},"frame":410,"tilemap":{"height":2,"tiles":[0,0,0,0],"width":2}},{"bounds":{"height":16,"x":0,"y":0,"width":16},"frame":411,"tilemap":{"height":2,"tiles":[0,0,0,0],"width":2}},{"bounds":{"height":16,"x":0,"y":0,"width":16},"frame":412,"tilemap":{"height":2,"tiles":[0,0,0,0],"width":2}},{"bounds":{"height":16,"x":0,"y":0,"width":16},"frame":413,"tilemap":{"height":2,"tiles":[0,0,0,0],"width":2}},{"bounds":{"height":16,"x":0,"y":0,"width":16},"frame":414,"tilemap":{"height":2,"tiles":[0,0,0,0],"width":2}},{"bounds":{"height":16,"x":0,"y":0,"width":16},"frame":415,"tilemap":{"height":2,"tiles":[0,0,0,0],"width":2}}],"name":"Sprite Sheet"}],"frames":[{"duration":0.1},{"duration":0.1},{"duration":0.1},{"duration":0.1},{"duration":0.1},{"duration":0.1},{"duration":0.1},{"duration":0.1},{"duration":0.1},{"duration":0.1},{"duration":0.1},{"duration":0.1},{"duration":0.1},{"duration":0.1},{"duration":0.1},{"duration":0.1},{"duration":0.1},{"duration":0.1},{"duration":0.1},{"duration":0.1},{"duration":0.1},{"duration":0.1},{"duration":0.1},{"duration":0.1},{"duration":0.1},{"duration":0.1},{"duration":0.1},{"duration":0.1},{"duration":0.1},{"duration":0.1},{"duration":0.1},{"duration":0.1},{"duration":0.1},{"duration":0.1},{"duration":0.1},{"duration":0.1},{"duration":0.1},{"duration":0.1},{"duration":0.1},{"duration":0.1},{"duration":0.1},{"duration":0.1},{"duration":0.1},{"duration":0.1},{"duration":0.1},{"duration":0.1},{"duration":0.1},{"duration":0.1},{"duration":0.1},{"duration":0.1},{"duration":0.1},{"duration":0.1},{"duration":0.1},{"duration":0.1},{"duration":0.1},{"duration":0.1},{"duration":0.1},{"duration":0.1},{"duration":0.1},{"duration":0.1},{"duration":0.1},{"duration":0.1},{"duration":0.1},{"duration":0.1},{"duration":0.1},{"duration":0.1},{"duration":0.1},{"duration":0.1},{"duration":0.1},{"duration":0.1},{"duration":0.1},{"duration":0.1},{"duration":0.1},{"duration":0.1},{"duration":0.1},{"duration":0.1},{"duration":0.1},{"duration":0.1},{"duration":0.1},{"duration":0.1},{"duration":0.1},{"duration":0.1},{"duration":0.1},{"duration":0.1},{"duration":0.1},{"duration":0.1},{"duration":0.1},{"duration":0.1},{"duration":0.1},{"duration":0.1},{"duration":0.1},{"duration":0.1},{"duration":0.1},{"duration":0.1},{"duration":0.1},{"duration":0.1},{"duration":0.1},{"duration":0.1},{"duration":0.1},{"duration":0.1},{"duration":0.1},{"duration":0.1},{"duration":0.1},{"duration":0.1},{"duration":0.1},{"duration":0.1},{"duration":0.1},{"duration":0.1},{"duration":0.1},{"duration":0.1},{"duration":0.1},{"duration":0.1},{"duration":0.1},{"duration":0.1},{"duration":0.1},{"duration":0.1},{"duration":0.1},{"duration":0.1},{"duration":0.1},{"duration":0.1},{"duration":0.1},{"duration":0.1},{"duration":0.1},{"duration":0.1},{"duration":0.1},{"duration":0.1},{"duration":0.1},{"duration":0.1},{"duration":0.1},{"duration":0.1},{"duration":0.1},{"duration":0.1},{"duration":0.1},{"duration":0.1},{"duration":0.1},{"duration":0.1},{"duration":0.1},{"duration":0.1},{"duration":0.1},{"duration":0.1},{"duration":0.1},{"duration":0.1},{"duration":0.1},{"duration":0.1},{"duration":0.1},{"duration":0.1},{"duration":0.1},{"duration":0.1},{"duration":0.1},{"duration":0.1},{"duration":0.1},{"duration":0.1},{"duration":0.1},{"duration":0.1},{"duration":0.1},{"duration":0.1},{"duration":0.1},{"duration":0.1},{"duration":0.1},{"duration":0.1},{"duration":0.1},{"duration":0.1},{"duration":0.1},{"duration":0.1},{"duration":0.1},{"duration":0.1},{"duration":0.1},{"duration":0.1},{"duration":0.1},{"duration":0.1},{"duration":0.1},{"duration":0.1},{"duration":0.1},{"duration":0.1},{"duration":0.1},{"duration":0.1},{"duration":0.1},{"duration":0.1},{"duration":0.1},{"duration":0.1},{"duration":0.1},{"duration":0.1},{"duration":0.1},{"duration":0.1},{"duration":0.1},{"duration":0.1},{"duration":0.1},{"duration":0.1},{"duration":0.1},{"duration":0.1},{"duration":0.1},{"duration":0.1},{"duration":0.1},{"duration":0.1},{"duration":0.1},{"duration":0.1},{"duration":0.1},{"duration":0.1},{"duration":0.1},{"duration":0.1},{"duration":0.1},{"duration":0.1},{"duration":0.1},{"duration":0.1},{"duration":0.1},{"duration":0.1},{"duration":0.1},{"duration":0.1},{"duration":0.1},{"duration":0.1},{"duration":0.1},{"duration":0.1},{"duration":0.1},{"duration":0.1},{"duration":0.1},{"duration":0.1},{"duration":0.1},{"duration":0.1},{"duration":0.1},{"duration":0.1},{"duration":0.1},{"duration":0.1},{"duration":0.1},{"duration":0.1},{"duration":0.1},{"duration":0.1},{"duration":0.1},{"duration":0.1},{"duration":0.1},{"duration":0.1},{"duration":0.1},{"duration":0.1},{"duration":0.1},{"duration":0.1},{"duration":0.1},{"duration":0.1},{"duration":0.1},{"duration":0.1},{"duration":0.1},{"duration":0.1},{"duration":0.1},{"duration":0.1},{"duration":0.1},{"duration":0.1},{"duration":0.1},{"duration":0.1},{"duration":0.1},{"duration":0.1},{"duration":0.1},{"duration":0.1},{"duration":0.1},{"duration":0.1},{"duration":0.1},{"duration":0.1},{"duration":0.1},{"duration":0.1},{"duration":0.1},{"duration":0.1},{"duration":0.1},{"duration":0.1},{"duration":0.1},{"duration":0.1},{"duration":0.1},{"duration":0.1},{"duration":0.1},{"duration":0.1},{"duration":0.1},{"duration":0.1},{"duration":0.1},{"duration":0.1},{"duration":0.1},{"duration":0.1},{"duration":0.1},{"duration":0.1},{"duration":0.1},{"duration":0.1},{"duration":0.1},{"duration":0.1},{"duration":0.1},{"duration":0.1},{"duration":0.1},{"duration":0.1},{"duration":0.1},{"duration":0.1},{"duration":0.1},{"duration":0.1},{"duration":0.1},{"duration":0.1},{"duration":0.1},{"duration":0.1},{"duration":0.1},{"duration":0.1},{"duration":0.1},{"duration":0.1},{"duration":0.1},{"duration":0.1},{"duration":0.1},{"duration":0.1},{"duration":0.1},{"duration":0.1},{"duration":0.1},{"duration":0.1},{"duration":0.1},{"duration":0.1},{"duration":0.1},{"duration":0.1},{"duration":0.1},{"duration":0.1},{"duration":0.1},{"duration":0.1},{"duration":0.1},{"duration":0.1},{"duration":0.1},{"duration":0.1},{"duration":0.1},{"duration":0.1},{"duration":0.1},{"duration":0.1},{"duration":0.1},{"duration":0.1},{"duration":0.1},{"duration":0.1},{"duration":0.1},{"duration":0.1},{"duration":0.1},{"duration":0.1},{"duration":0.1},{"duration":0.1},{"duration":0.1},{"duration":0.1},{"duration":0.1},{"duration":0.1},{"duration":0.1},{"duration":0.1},{"duration":0.1},{"duration":0.1},{"duration":0.1},{"duration":0.1},{"duration":0.1},{"duration":0.1},{"duration":0.1},{"duration":0.1},{"duration":0.1},{"duration":0.1},{"duration":0.1},{"duration":0.1},{"duration":0.1},{"duration":0.1},{"duration":0.1},{"duration":0.1},{"duration":0.1},{"duration":0.1},{"duration":0.1},{"duration":0.1},{"duration":0.1},{"duration":0.1},{"duration":0.1},{"duration":0.1},{"duration":0.1},{"duration":0.1},{"duration":0.1},{"duration":0.1},{"duration":0.1},{"duration":0.1},{"duration":0.1},{"duration":0.1},{"duration":0.1},{"duration":0.1},{"duration":0.1},{"duration":0.1},{"duration":0.1},{"duration":0.1},{"duration":0.1},{"duration":0.1},{"duration":0.1},{"duration":0.1},{"duration":0.1},{"duration":0.1},{"duration":0.1},{"duration":0.1},{"duration":0.1},{"duration":0.1},{"duration":0.1},{"duration":0.1},{"duration":0.1},{"duration":0.1},{"duration":0.1},{"duration":0.1},{"duration":0.1},{"duration":0.1},{"duration":0.1},{"duration":0.1},{"duration":0.1},{"duration":0.1},{"duration":0.1},{"duration":0.1},{"duration":0.1},{"duration":0.1},{"duration":0.1},{"duration":0.1},{"duration":0.1},{"duration":0.1},{"duration":0.1},{"duration":0.1},{"duration":0.1},{"duration":0.1},{"duration":0.1},{"duration":0.1},{"duration":0.1},{"duration":0.1},{"duration":0.1},{"duration":0.1},{"duration":0.1},{"duration":0.1},{"duration":0.1},{"duration":0.1}]}